sacredfig/__init__.py
sacredfig/main.py
sacredfig/sacredfig.mplstyle
sacredfig/seaborn.py
sacredfig-0.1.1.dist-info/METADATA
sacredfig-0.1.1.dist-info/WHEEL
sacredfig-0.1.1.dist-info/RECORD
