Metadata-Version: 2.1
Name: sacredfig
Version: 0.1.1
Summary: An opinionated library for scientific figures in matplotlib.
Home-page: https://github.com/cynddl/sacredfig
License: MIT
Keywords: matplotlib,data-visualization,scientific-figures,plotting
Author: Luc Rocher
Author-email: luc@rocher.lc
Requires-Python: >=3.8,<4.0
Classifier: Development Status :: 4 - Beta
Classifier: Intended Audience :: Developers
Classifier: Intended Audience :: Science/Research
Classifier: License :: OSI Approved :: MIT License
Classifier: Programming Language :: Python
Classifier: Programming Language :: Python :: 3
Classifier: Programming Language :: Python :: 3.8
Classifier: Programming Language :: Python :: 3.9
Classifier: Programming Language :: Python :: 3.10
Classifier: Programming Language :: Python :: 3.11
Classifier: Programming Language :: Python :: 3.12
Classifier: Topic :: Scientific/Engineering :: Visualization
Requires-Dist: matplotlib (>=3.6,<4.0)
Project-URL: Repository, https://github.com/cynddl/sacredfig
